formsg/__init__.py
formsg/crypto.py
formsg_sdk-0.1.4.dist-info/METADATA
formsg_sdk-0.1.4.dist-info/WHEEL
formsg_sdk-0.1.4.dist-info/licenses/LICENSE
formsg_sdk-0.1.4.dist-info/RECORD
