Metadata-Version: 2.1
Name: formsg-sdk
Version: 0.1.4
Summary: Python SDK for FormSG
Project-URL: Homepage, https://github.com/shion-lee/formsg-sdk
Author-email: Shion Lee <shionlee92@gmail.com>
License-File: LICENSE
Classifier: License :: OSI Approved :: MIT License
Classifier: Operating System :: OS Independent
Classifier: Programming Language :: Python :: 3
Requires-Python: >=3.7
Requires-Dist: pynacl
Requires-Dist: requests
